dbapi_helper/__init__.py
dbapi_helper/connection.py
dbapi_helper/cursor.py
dbapi_helper/exceptions.py
dbapi_helper/py.typed
dbapi_helper/types.py
dbapi_helper-0.1.0.dist-info/METADATA
dbapi_helper-0.1.0.dist-info/WHEEL
dbapi_helper-0.1.0.dist-info/licenses/LICENSE
dbapi_helper-0.1.0.dist-info/RECORD
