Metadata-Version: 2.3
Name: dbapi-helper
Version: 0.1.0
Summary: A helper library for implementing Python DB API 2.0 database drivers
Project-URL: Homepage, https://github.com/betodealmeida/dbapi-helper
Project-URL: Repository, https://github.com/betodealmeida/dbapi-helper
Project-URL: Issues, https://github.com/betodealmeida/dbapi-helper/issues
Author-email: Beto Dealmeida <roberto@dealmeida.net>
License: Apache License 2.0
License-File: LICENSE
Keywords: database,db-api,dbapi,driver,sql
Classifier: Development Status :: 3 - Alpha
Classifier: Intended Audience :: Developers
Classifier: License :: OSI Approved :: Apache Software License
Classifier: Programming Language :: Python :: 3
Classifier: Programming Language :: Python :: 3.9
Classifier: Programming Language :: Python :: 3.10
Classifier: Programming Language :: Python :: 3.11
Classifier: Programming Language :: Python :: 3.12
Classifier: Programming Language :: Python :: 3.13
Classifier: Topic :: Database
Classifier: Topic :: Software Development :: Libraries :: Python Modules
Requires-Python: >=3.9
Provides-Extra: dev
Requires-Dist: build>=1.0; extra == 'dev'
Requires-Dist: mypy>=1.0; extra == 'dev'
Requires-Dist: pre-commit>=3.0; extra == 'dev'
Requires-Dist: pytest>=7.0; extra == 'dev'
Requires-Dist: twine>=4.0; extra == 'dev'
